percentipedecrawler/.env.example
percentipedecrawler/Crawler.py
percentipedecrawler/__init__.py
percentipedecrawler/database.py
percentipedecrawler/main.py
percentipedecrawler/models.py
percentipedecrawler/requirements.txt
percentipedecrawler/save.py
percentipedecrawler/setup.py
percentipedecrawler/utils/dockerFile.txt
percentipedecrawler-0.0.25.dist-info/METADATA
percentipedecrawler-0.0.25.dist-info/WHEEL
percentipedecrawler-0.0.25.dist-info/licenses/LICENSE
percentipedecrawler-0.0.25.dist-info/RECORD
